driver/__init__.py
driver/cinder.conf.sample
driver/common.py
driver/freenasapi.py
driver/iscsi.py
driver/loadenv.py
driver/options.py
driver/utils.py
databunnystoragedriver-1.1.16.dev5.dist-info/AUTHORS
databunnystoragedriver-1.1.16.dev5.dist-info/LICENSE
databunnystoragedriver-1.1.16.dev5.dist-info/METADATA
databunnystoragedriver-1.1.16.dev5.dist-info/WHEEL
databunnystoragedriver-1.1.16.dev5.dist-info/pbr.json
databunnystoragedriver-1.1.16.dev5.dist-info/top_level.txt
databunnystoragedriver-1.1.16.dev5.dist-info/RECORD
